lightpath/__init__.py
lightpath/__main__.py
lightpath/_version.py
lightpath/config.py
lightpath/controller.py
lightpath/errors.py
lightpath/main.py
lightpath/mock_devices.py
lightpath/path.py
lightpath/version.py
lightpath/happi/__init__.py
lightpath/happi/containers.py
lightpath/tests/__init__.py
lightpath/tests/conf.yml
lightpath/tests/conftest.py
lightpath/tests/path.json
lightpath/tests/test_cli.py
lightpath/tests/test_controller.py
lightpath/tests/test_gui.py
lightpath/tests/test_path.py
lightpath/tests/test_widgets.py
lightpath/ui/__init__.py
lightpath/ui/device.ui
lightpath/ui/gui.py
lightpath/ui/lightapp.ui
lightpath/ui/widgets.py
lightpath-1.0.7.dist-info/licenses/AUTHORS.rst
lightpath-1.0.7.dist-info/licenses/LICENSE.md
lightpath-1.0.7.dist-info/METADATA
lightpath-1.0.7.dist-info/WHEEL
lightpath-1.0.7.dist-info/entry_points.txt
lightpath-1.0.7.dist-info/top_level.txt
lightpath-1.0.7.dist-info/RECORD
