Metadata-Version: 2.4
Name: lightpath
Version: 1.0.7
Summary: {{ cookiecutter.description }}
Author: SLAC National Accelerator Laboratory
License: Copyright (c) 2023, The Board of Trustees of the Leland Stanford Junior
Classifier: Development Status :: 2 - Pre-Alpha
Classifier: Natural Language :: English
Classifier: Programming Language :: Python :: 3
Requires-Python: >=3.9
License-File: LICENSE.md
License-File: AUTHORS.rst
Requires-Dist: coloredlogs
Requires-Dist: happi>=1.6.0
Requires-Dist: numpy
Requires-Dist: ophyd
Requires-Dist: networkx<3.3
Requires-Dist: prettytable
Provides-Extra: gui
Requires-Dist: pydm; extra == "gui"
Requires-Dist: PyQt5; extra == "gui"
Requires-Dist: qtawesome; extra == "gui"
Requires-Dist: qtpy; extra == "gui"
Requires-Dist: typhos>=1.0.0; extra == "gui"
Provides-Extra: doc
Requires-Dist: docs-versions-menu; extra == "doc"
Requires-Dist: sphinx; extra == "doc"
Requires-Dist: sphinx_rtd_theme>=1.2.0; extra == "doc"
Requires-Dist: sphinx-argparse; extra == "doc"
Requires-Dist: sphinxcontrib-jquery; extra == "doc"
Provides-Extra: test
Requires-Dist: pytest; extra == "test"
Requires-Dist: ipython; extra == "test"
Requires-Dist: matplotlib; extra == "test"
Requires-Dist: flake8; extra == "test"
Requires-Dist: pytest-cov; extra == "test"
Requires-Dist: pytest-qt; extra == "test"
Requires-Dist: pydm; extra == "test"
Requires-Dist: PyQt5; extra == "test"
Requires-Dist: qtawesome; extra == "test"
Requires-Dist: qtpy; extra == "test"
Requires-Dist: typhos>=1.0.0; extra == "test"
Dynamic: license-file
